{"type": "Feature", "id": 40995, "properties": {"woe:id": 40995, "woe:parent_id": 12695968, "woe:name": "Woodmancott", "woe:placetype": 7, "woe:placetype_name": "Town", "woe:lang": "ENG", "iso:country": "GB", "meta:provider": ["geoplanet:7.3.1", "geoplanet:7.3.2", "geoplanet:7.4.0", "geoplanet:7.4.1", "geoplanet:7.5.1", "geoplanet:7.5.2", "geoplanet:7.6.0", "geoplanet:7.8.1", "geoplanet:7.9.0", "geoplanet:7.10.0", "geoplanet:8.0.0", "woeplanet:8.0.0"], "meta:indexed": "2020-08-20T19:45:10.549302", "meta:updated": "2020-09-19T16:05:01.215091", "woe:adjacent": [28796, 32337, 19095, 14246], "woe:hierarchy": {"continent": 24865675, "country": 23424975, "town": 0, "planet": 1, "county": 12602169, "suburb": 0, "state": 24554868, "region": 0, "localadmin": 12695968}, "woe:timezone_id": 28350903, "woe:concordances": {"qs:id": 110326}, "woe:hash": "gcp5hucft68b", "geom:min_latitude": 51.178879, "woe:centroid": [-1.19488, 51.178879], "geom:latitude": 51.178879, "woe:max_longitude": -1.19488, "geom:max_longitude": -1.19488, "geom:centroid": [-1.19488, 51.178879], "geom:max_latitude": 51.178879, "woe:min_latitude": 51.178879, "woe:min_longitude": -1.19488, "geom:longitude": -1.19488, "geom:hash": "gcp5hucft68b", "woe:latitude": 51.178879, "geom:min_longitude": -1.19488, "woe:longitude": -1.19488, "woe:max_latitude": 51.178879, "woe:children": {"zip": [27954564, 27954565]}, "woe:repo": "woeplanet-town-gb"}, "geometry": {"coordinates": [-1.19488, 51.178879], "type": "Point"}}