{"type": "Feature", "id": 18189, "geometry": {"type": "Point", "coordinates": [-4.89863, 52.012589]}, "properties": {"woe:id": 18189, "woe:parent_id": 12696129, "woe:name": "Dinas Cross", "woe:placetype": 7, "woe:placetype_name": "Town", "woe:lang": "ENG", "iso:country": "GB", "meta:provider": ["geoplanet:7.3.1", "geoplanet:7.3.2", "geoplanet:7.4.0", "geoplanet:7.4.1", "geoplanet:7.5.1", "geoplanet:7.5.2", "geoplanet:7.6.0", "geoplanet:7.8.1", "geoplanet:7.9.0", "geoplanet:7.10.0", "geoplanet:8.0.0", "woeplanet:8.0.0"], "meta:indexed": "2020-08-20T19:45:05.149536", "woe:alias_ENG_V": ["Dinas"], "meta:updated": "2020-10-14T12:02:18.890287", "woe:adjacent": [27826, 27141, 20092313, 32289], "woe:hierarchy": {"continent": 24865675, "country": 23424975, "town": 0, "planet": 1, "county": 12602226, "suburb": 0, "state": 12578049, "region": 0, "localadmin": 12696129}, "woe:timezone_id": 28350903, "woe:concordances": {"gn:id": 7301099, "qs:id": 1249293}, "woe:hash": "gchxbs8gm9kd", "geom:min_latitude": 52.012589, "woe:centroid": [-4.89863, 52.012589], "geom:latitude": 52.012589, "woe:max_longitude": -4.89863, "geom:max_longitude": -4.89863, "geom:centroid": [-4.89863, 52.012589], "geom:max_latitude": 52.012589, "woe:min_latitude": 52.012589, "woe:min_longitude": -4.89863, "geom:longitude": -4.89863, "geom:hash": "gchxbs8gm9kd", "woe:latitude": 52.012589, "geom:min_longitude": -4.89863, "woe:longitude": -4.89863, "woe:max_latitude": 52.012589, "woe:children": {"zip": [27880917]}, "woe:repo": "woeplanet-town-gb", "geom:area": 0.0, "woe:scale": 16}}